README.md
setup.py
bm_inventory_client/__init__.py
bm_inventory_client/api_client.py
bm_inventory_client/configuration.py
bm_inventory_client/rest.py
bm_inventory_client.egg-info/PKG-INFO
bm_inventory_client.egg-info/SOURCES.txt
bm_inventory_client.egg-info/dependency_links.txt
bm_inventory_client.egg-info/requires.txt
bm_inventory_client.egg-info/top_level.txt
bm_inventory_client/api/__init__.py
bm_inventory_client/api/events_api.py
bm_inventory_client/api/installer_api.py
bm_inventory_client/api/versions_api.py
bm_inventory_client/models/__init__.py
bm_inventory_client/models/block_device.py
bm_inventory_client/models/boot.py
bm_inventory_client/models/cidr.py
bm_inventory_client/models/cluster.py
bm_inventory_client/models/cluster_create_params.py
bm_inventory_client/models/cluster_list.py
bm_inventory_client/models/cluster_update_params.py
bm_inventory_client/models/clusterupdateparams_hosts_roles.py
bm_inventory_client/models/connectivity_check_host.py
bm_inventory_client/models/connectivity_check_nic.py
bm_inventory_client/models/connectivity_check_params.py
bm_inventory_client/models/connectivity_remote_host.py
bm_inventory_client/models/connectivity_report.py
bm_inventory_client/models/cpu.py
bm_inventory_client/models/cpu_details.py
bm_inventory_client/models/credentials.py
bm_inventory_client/models/debug_step.py
bm_inventory_client/models/disk.py
bm_inventory_client/models/error.py
bm_inventory_client/models/event.py
bm_inventory_client/models/event_list.py
bm_inventory_client/models/free_addresses_request.py
bm_inventory_client/models/free_network_addresses.py
bm_inventory_client/models/free_networks_addresses.py
bm_inventory_client/models/host.py
bm_inventory_client/models/host_create_params.py
bm_inventory_client/models/host_install_progress_params.py
bm_inventory_client/models/host_list.py
bm_inventory_client/models/host_network.py
bm_inventory_client/models/image_create_params.py
bm_inventory_client/models/image_info.py
bm_inventory_client/models/ingress_cert_params.py
bm_inventory_client/models/interface.py
bm_inventory_client/models/introspection.py
bm_inventory_client/models/inventory.py
bm_inventory_client/models/l2_connectivity.py
