Metadata-Version: 1.0
Name: bm-inventory-client
Version: 1.0.0
Summary: AssistedInstall
Home-page: UNKNOWN
Author: UNKNOWN
Author-email: UNKNOWN
License: UNKNOWN
Keywords: Swagger,AssistedInstall
Platform: UNKNOWN
